[
  {
    "name": "noschema",
    "description": "file without schema",
    "fileMatch": []
  },
  {
    "name": "dot",
    "description": "jsona config file",
    "fileMatch": [
      "**/.jsona"
    ]
  },
  {
    "name": "apitest",
    "description": "apitest file",
    "fileMatch": [
      "**/*.apitest.jsona",
      "**/test*/*.jsona"
    ]
  },
  {
    "name": "openapi",
    "description": "openapi file",
    "fileMatch": [
      "**/*.openapi.jsona",
      "**/api*.jsona"
    ]
  },
  {
    "name": "schema",
    "description": "jsonaschema file",
    "fileMatch": [
      "**/*.schema.jsona"
    ]
  }
]